odoo/addons/hotel_reservation/README.rst
odoo/addons/hotel_reservation/__init__.py
odoo/addons/hotel_reservation/__manifest__.py
odoo/addons/hotel_reservation/LICENSE/LICENSE
odoo/addons/hotel_reservation/data/email_template_view.xml
odoo/addons/hotel_reservation/data/hotel_reservation_data.xml
odoo/addons/hotel_reservation/data/hotel_reservation_sequence.xml
odoo/addons/hotel_reservation/data/hotel_scheduler.xml
odoo/addons/hotel_reservation/i18n/da.po
odoo/addons/hotel_reservation/i18n/es.po
odoo/addons/hotel_reservation/i18n/fr.po
odoo/addons/hotel_reservation/i18n/fr_BE.po
odoo/addons/hotel_reservation/i18n/fr_FR.po
odoo/addons/hotel_reservation/i18n/hotel_reservation.pot
odoo/addons/hotel_reservation/i18n/pt_BR.po
odoo/addons/hotel_reservation/i18n/sv.po
odoo/addons/hotel_reservation/i18n/zh_CN.po
odoo/addons/hotel_reservation/models/__init__.py
odoo/addons/hotel_reservation/models/hotel_reservation.py
odoo/addons/hotel_reservation/readme/CONTRIBUTORS.rst
odoo/addons/hotel_reservation/readme/DESCRIPTION.rst
odoo/addons/hotel_reservation/report/__init__.py
odoo/addons/hotel_reservation/report/checkin_report_template.xml
odoo/addons/hotel_reservation/report/checkout_report_template.xml
odoo/addons/hotel_reservation/report/hotel_reservation_report.py
odoo/addons/hotel_reservation/report/hotel_reservation_report_template.xml
odoo/addons/hotel_reservation/report/report_view.xml
odoo/addons/hotel_reservation/report/room_max_report_template.xml
odoo/addons/hotel_reservation/security/ir.model.access.csv
odoo/addons/hotel_reservation/security/reservation_security.xml
odoo/addons/hotel_reservation/static/description/HotelReserv.png
odoo/addons/hotel_reservation/static/description/done.png
odoo/addons/hotel_reservation/static/description/folio.png
odoo/addons/hotel_reservation/static/description/icon.png
odoo/addons/hotel_reservation/static/description/index.html
odoo/addons/hotel_reservation/static/description/res5.png
odoo12_addon_hotel_reservation-12.0.1.0.0.99.dev37.dist-info/METADATA
odoo12_addon_hotel_reservation-12.0.1.0.0.99.dev37.dist-info/WHEEL
odoo12_addon_hotel_reservation-12.0.1.0.0.99.dev37.dist-info/top_level.txt
odoo12_addon_hotel_reservation-12.0.1.0.0.99.dev37.dist-info/RECORD
