Metadata-Version: 2.1
Name: odoo12-addon-hotel-reservation
Version: 12.0.1.0.0.99.dev37
Summary: Manages Guest Reservation & displays Reservation Summary
Home-page: https://github.com/OCA/vertical-hotel/
Author: Odoo Community Association (OCA), Serpent Consulting Services Pvt. Ltd., Odoo S.A.
Author-email: support@odoo-community.org
License: AGPL-3
Platform: UNKNOWN
Classifier: Programming Language :: Python
Classifier: Framework :: Odoo
Classifier: Framework :: Odoo :: 12.0
Classifier: License :: OSI Approved :: GNU Affero General Public License v3
Requires-Python: >=3.5
Requires-Dist: odoo12-addon-hotel
Requires-Dist: odoo <12.1dev,>=12.0a
Requires-Dist: python-dateutil
